{"httpProtocol":"HTTP/1.1","clientAcceptEncoding":"gzip, deflate, br","requestPriority":"","edgeRequestKeepAliveStatus":1,"requestHeaderNames":{},"clientTcpRtt":9,"colo":"ICN","asn":4766,"asOrganization":"Korea Telecom","country":"KR","isEUCountry":false,"city":"Cheonan","continent":"AS","region":"Chungcheongnam-do","regionCode":"44","timezone":"Asia/Seoul","longitude":"127.1522","latitude":"36.8065","postalCode":"31126","tlsVersion":"TLSv1.3","tlsCipher":"AEAD-AES256-GCM-SHA384","tlsClientRandom":"CBHOHVVmVhrNeTqVjDoutMaDOt2QPqRvjEa7aGdQuvY=","tlsClientCiphersSha1":"kXrN3VEKDdzz2cPKTQaKzpxVTxQ=","tlsClientExtensionsSha1":"1eY97BUYYO8vDaTfHQywB1pcNdM=","tlsClientExtensionsSha1Le":"u4wtEMFQBY18l3BzHAvORm+KGRw=","tlsExportedAuthenticator":{"clientHandshake":"d5b893d7989a2ef6b50663be26a3f7b8222e10c203567a438477cb7486e3e5337d21a4ae3f85a3878d9e3f40bb3e77ab","serverHandshake":"e39d826a14a242be3d32cda4f87d5315c0894dd850d1550e6ab179aaacdabdb5b54c5a3ac7d2051bbd6bd1080614ff42","clientFinished":"64a641d31227a623fd4bbefaa7e9b772f0aaa9b15bb07616f6d75173435a03a5a8c005f42a67c9c38d4f11d8c0036552","serverFinished":"ad362789f3a10d8e45c546c2a3d0be1ab3f7d0d3225dd6d4b020225bc73f9464e48d11500c31e6706a8d6f3a366061cb"},"tlsClientHelloLength":"1605","tlsClientAuth":{"certPresented":"0","certVerified":"NONE","certRevoked":"0","certIssuerDN":"","certSubjectDN":"","certIssuerDNRFC2253":"","certSubjectDNRFC2253":"","certIssuerDNLegacy":"","certSubjectDNLegacy":"","certSerial":"","certIssuerSerial":"","certSKI":"","certIssuerSKI":"","certFingerprintSHA1":"","certFingerprintSHA256":"","certNotBefore":"","certNotAfter":""},"verifiedBotCategory":"","botManagement":{"corporateProxy":false,"verifiedBot":false,"jsDetection":{"passed":false},"staticResource":false,"detectionIds":{},"score":99}}